{"cameraMode":{"drawMode":0,"name":"Shaded","section":"Shading Mode"},"sceneLighting":false,"audioPlay":false,"sceneViewState":{"showFog":true,"showMaterialUpdate":false,"showSkybox":false,"showFlares":true,"showImageEffects":true,"showParticleSystems":true},"in2DMode":false,"pivot":{"x":53.817684173583987,"y":2.5831897258758547,"z":-13.086706161499024},"rotation":{"x":0.18131646513938905,"y":0.5578965544700623,"z":-0.12645497918128968,"w":0.7999298572540283},"size":20.598819732666017,"orthographic":false}